correctiv_sortabletable-0.0.8.dist-info/DESCRIPTION.rst
correctiv_sortabletable-0.0.8.dist-info/METADATA
correctiv_sortabletable-0.0.8.dist-info/RECORD
correctiv_sortabletable-0.0.8.dist-info/WHEEL
correctiv_sortabletable-0.0.8.dist-info/metadata.json
correctiv_sortabletable-0.0.8.dist-info/pbr.json
correctiv_sortabletable-0.0.8.dist-info/top_level.txt
sortable_table/__init__.py
sortable_table/cms_plugins.py
sortable_table/models.py
sortable_table/locale/de/LC_MESSAGES/django.mo
sortable_table/locale/de/LC_MESSAGES/django.po
sortable_table/locale/en/LC_MESSAGES/django.mo
sortable_table/locale/en/LC_MESSAGES/django.po
sortable_table/migrations/0001_initial.py
sortable_table/migrations/0002_sortabletableplugin_source.py
sortable_table/migrations/__init__.py
sortable_table/static/sortable_table/css/main.css
sortable_table/static/sortable_table/js/main.js
sortable_table/static/sortable_table/js/vendor/chroma-js/chroma.min.js
sortable_table/static/sortable_table/js/vendor/tablesort/tablesort.min.js
sortable_table/static/sortable_table/js/vendor/tablesort/src/sorts/tablesort.numeric.js
sortable_table/templates/sortable_table/render_table.html
sortabletable/__init__.py
sortabletable/cms_plugins.py
sortabletable/models.py
sortabletable/locale/de/LC_MESSAGES/django.mo
sortabletable/locale/de/LC_MESSAGES/django.po
sortabletable/locale/en/LC_MESSAGES/django.mo
sortabletable/locale/en/LC_MESSAGES/django.po
sortabletable/migrations/0001_initial.py
sortabletable/migrations/0002_sortabletableplugin_source.py
sortabletable/migrations/__init__.py
sortabletable/static/sortabletable/css/main.css
sortabletable/static/sortabletable/js/main.js
sortabletable/static/sortabletable/js/vendor/chroma-js/chroma.min.js
sortabletable/static/sortabletable/js/vendor/tablesort/tablesort.min.js
sortabletable/static/sortabletable/js/vendor/tablesort/src/sorts/tablesort.numeric.js
sortabletable/templates/sortabletable/render_table.html
