Metadata-Version: 2.0
Name: correctiv-sortabletable
Version: 0.0.8
Summary: Sortable Table Django CMS Plugin
Home-page: https://github.org/correctiv/correctiv-sortabletable
Author: Stefan Wehrmeyer
Author-email: stefan.wehrmeyer@correctiv.org
License: MIT
Platform: UNKNOWN
Classifier: Development Status :: 5 - Production/Stable
Classifier: Environment :: Web Environment
Classifier: Framework :: Django
Classifier: Intended Audience :: Developers
Classifier: License :: OSI Approved :: MIT License
Classifier: Natural Language :: English
Classifier: Operating System :: OS Independent
Classifier: Programming Language :: Python :: 2.7
Classifier: Topic :: Internet :: WWW/HTTP
Requires-Dist: Django
Requires-Dist: django-cms
Requires-Dist: django-markdown-deux
Requires-Dist: jsonfield
Requires-Dist: unicodecsv
